LICENSE
awstt/__init__.py
awstt/__main__.py
awstt/cli.py
awstt/config.py
awstt/evals.py
awstt/executor.py
awstt/lambda.py
awstt/output.py
awstt/worker/__init__.py
awstt/worker/registrable.py
awstt/worker/scanner.py
awstt/worker/scanners/__init__.py
awstt/worker/scanners/cloudformation.py
awstt/worker/scanners/cloudfront_distribution.py
awstt/worker/scanners/cloudtrail.py
awstt/worker/scanners/cloudwatch_alarm.py
awstt/worker/scanners/cloudwatch_loggroup.py
awstt/worker/scanners/cloudwatch_rules.py
awstt/worker/scanners/dynamodb_table.py
awstt/worker/scanners/ec2_ami.py
awstt/worker/scanners/ec2_autoscaling.py
awstt/worker/scanners/ec2_ebs.py
awstt/worker/scanners/ec2_eip.py
awstt/worker/scanners/ec2_eni.py
awstt/worker/scanners/ec2_instance.py
awstt/worker/scanners/ec2_internet_gateway.py
awstt/worker/scanners/ec2_nat_gateway.py
awstt/worker/scanners/ec2_network_acl.py
awstt/worker/scanners/ec2_routetable.py
awstt/worker/scanners/ec2_securitygroup.py
awstt/worker/scanners/ec2_snapshot.py
awstt/worker/scanners/ec2_subnet.py
awstt/worker/scanners/ec2_vpc.py
awstt/worker/scanners/ec2_vpc_peering.py
awstt/worker/scanners/ec2_vpn_gateway.py
awstt/worker/scanners/efs.py
awstt/worker/scanners/elasticache_cluster.py
awstt/worker/scanners/elasticache_snapshot.py
awstt/worker/scanners/elasticsearch.py
awstt/worker/scanners/elb.py
awstt/worker/scanners/emr_cluster.py
awstt/worker/scanners/emr_studio.py
awstt/worker/scanners/iam_policy.py
awstt/worker/scanners/iam_role.py
awstt/worker/scanners/iam_user.py
awstt/worker/scanners/kms.py
awstt/worker/scanners/lambda_function.py
awstt/worker/scanners/lightsail_instance.py
awstt/worker/scanners/opensearch.py
awstt/worker/scanners/rds_cluster.py
awstt/worker/scanners/rds_instance.py
awstt/worker/scanners/s3_bucket.py
awstt/worker/tagger.py
awstt/worker/thread.py
awstt/worker/types.py
awstt/worker/utils.py
aws_tag_tools-1.1.1.dist-info/LICENSE
aws_tag_tools-1.1.1.dist-info/METADATA
aws_tag_tools-1.1.1.dist-info/WHEEL
aws_tag_tools-1.1.1.dist-info/entry_points.txt
aws_tag_tools-1.1.1.dist-info/RECORD
