Metadata-Version: 2.1
Name: aws-tag-tools
Version: 1.1.1
Summary: The unified tag manager for AWS resources
Home-page: https://github.com/anyions/aws-tag-tools
License: MIT
Author: AnyIons
Author-email: anyions@hotmail.com
Maintainer: AnyIons
Maintainer-email: anyions@hotmail.com
Requires-Python: >=3.11,<4.0
Classifier: Development Status :: 5 - Production/Stable
Classifier: Environment :: Console
Classifier: Intended Audience :: Developers
Classifier: Intended Audience :: Information Technology
Classifier: Intended Audience :: System Administrators
Classifier: License :: OSI Approved :: MIT License
Classifier: Operating System :: OS Independent
Classifier: Programming Language :: Python
Classifier: Programming Language :: Python :: 3
Classifier: Programming Language :: Python :: 3.11
Classifier: Programming Language :: Python :: 3.12
Classifier: Topic :: Utilities
Requires-Dist: boto3 (>=1.34.104,<2.0.0)
Requires-Dist: rich (>=13.9.2,<14.0.0)
Requires-Dist: rich-click (>=1.8.3,<2.0.0)
Project-URL: Repository, https://github.com/anyions/aws-tag-tools
